[
	{
		"name": "Baby Yoda",
		"identifier": "a1",
		"length": 10
	},
	{
		"name": "Baby Yoda",
		"identifier": "b1",
		"length": 20
	},
	{
		"name": "Baby Yoda",
		"identifier": "b2",
		"length": 20
	},
	{
		"name": "Baby Yoda",
		"identifier": "b3",
		"length": 12
	},
	{
		"name": "Baby Yoda",
		"identifier": "b4",
		"length": 14
	},
	{
		"name": "Baby Yoda",
		"identifier": "b5",
		"length": 24
	},
	{
		"name": "Baby Yoda",
		"identifier": "b6",
		"length": 14
	},
	{
		"name": "Baby Yoda",
		"identifier": "b7",
		"length": 14
	},
	{
		"name": "Baby Yoda",
		"identifier": "b8",
		"length": 9
	},
	{
		"name": "Baby Yoda",
		"identifier": "b9",
		"length": 10
	},
	{
		"name": "Baby Yoda",
		"identifier": "c1",
		"length": 28
	},
	{
		"name": "Baby Yoda",
		"identifier": "c2",
		"length": 20
	},
	{
		"name": "Baby Yoda",
		"identifier": "c3",
		"length": 20
	},
	{
		"name": "Baby Yoda",
		"identifier": "c4",
		"length": 25
	},
	{
		"name": "Baby Yoda",
		"identifier": "c5",
		"length": 23
	},
	{
		"name": "Baby Yoda",
		"identifier": "c6",
		"length": 10
	},
	{
		"name": "Baby Yoda",
		"identifier": "c7",
		"length": 27
	},
	{
		"name": "Baby Yoda",
		"identifier": "c8",
		"length": 6
	},
	{
		"name": "Baby Yoda",
		"identifier": "c9",
		"length": 11
	},
	{
		"name": "Baby Yoda",
		"identifier": "c10",
		"length": 22
	},
	{
		"name": "Baby Yoda",
		"identifier": "c11",
		"length": 11
	},
	{
		"name": "Baby Yoda",
		"identifier": "c12",
		"length": 15
	},
	{
		"name": "Baby Yoda",
		"identifier": "c13",
		"length": 16
	},
	{
		"name": "Baby Yoda",
		"identifier": "c14",
		"length": 20
	},
	{
		"name": "Baby Yoda",
		"identifier": "c15",
		"length": 20
	},
	{
		"name": "Baby Yoda",
		"identifier": "c16",
		"length": 24
	},
	{
		"name": "Baby Yoda",
		"identifier": "c17",
		"length": 20
	},
	{
		"name": "Baby Yoda",
		"identifier": "c18",
		"length": 10
	},
	{
		"name": "Baby Yoda",
		"identifier": "d1",
		"length": 19
	},
	{
		"name": "Baby Yoda",
		"identifier": "d2",
		"length": 25
	},
	{
		"name": "Baby Yoda",
		"identifier": "d3",
		"length": 28
	},
	{
		"name": "Baby Yoda",
		"identifier": "d4",
		"length": 9
	},
	{
		"name": "Baby Yoda",
		"identifier": "d5",
		"length": 16
	},
	{
		"name": "Baby Yoda",
		"identifier": "d6",
		"length": 29
	},
	{
		"name": "Baby Yoda",
		"identifier": "d7",
		"length": 30
	},
	{
		"name": "Baby Yoda",
		"identifier": "d8",
		"length": 6
	},
	{
		"name": "Baby Yoda",
		"identifier": "d9",
		"length": 25
	},
	{
		"name": "Baby Yoda",
		"identifier": "d10",
		"length": 20
	},
	{
		"name": "Baby Yoda",
		"identifier": "d11",
		"length": 20
	},
	{
		"name": "Baby Yoda",
		"identifier": "e1",
		"length": 27
	},
	{
		"name": "Baby Yoda",
		"identifier": "f1",
		"length": 20
	},
	{
		"name": "Baby Yoda",
		"identifier": "f2",
		"length": 20
	},
	{
		"name": "Baby Yoda",
		"identifier": "f3",
		"length": 13
	},
	{
		"name": "Baby Yoda",
		"identifier": "f4",
		"length": 14
	},
	{
		"name": "Baby Yoda",
		"identifier": "f5",
		"length": 24
	},
	{
		"name": "Baby Yoda",
		"identifier": "f6",
		"length": 14
	},
	{
		"name": "Baby Yoda",
		"identifier": "f7",
		"length": 14
	},
	{
		"name": "Baby Yoda",
		"identifier": "f8",
		"length": 9
	},
	{
		"name": "Baby Yoda",
		"identifier": "f9",
		"length": 10
	},
	{
		"name": "Baby Yoda",
		"identifier": "g1",
		"length": 30
	},
	{
		"name": "Spanish Yoda",
		"identifier": "g2",
		"length": 27
	},
	{
		"name": "Christmas Yoda",
		"identifier": "g3",
		"length": 6
	},
	{
		"name": "Celebration Yoda",
		"identifier": "g4",
		"length": 11
	},
	{
		"name": "Funny Yoda",
		"identifier": "g5",
		"length": 22
	},
	{
		"name": "English Yoda",
		"identifier": "g6",
		"length": 11
	},
	{
		"name": "Spanish Yoda",
		"identifier": "g7",
		"length": 15
	},
	{
		"name": "Valentines Day",
		"identifier": "g8",
		"length": 16
	},
	{
		"name": "Baby Yoda",
		"identifier": "h1",
		"length": 10
	},
	{
		"name": "Baby Yoda",
		"identifier": "h2",
		"length": 10
	},
	{
		"name": "Baby Yoda",
		"identifier": "h3",
		"length": 10
	},
	{
		"name": "Baby Yoda",
		"identifier": "h4",
		"length": 10
	},
	{
		"name": "Baby Yoda",
		"identifier": "h5",
		"length": 10
	},
	{
		"name": "Baby Yoda",
		"identifier": "h6",
		"length": 10
	},
	{
		"name": "Baby Yoda",
		"identifier": "h7",
		"length": 10
	},
	{
		"name": "Baby Yoda",
		"identifier": "i2",
		"length": 10
	},
	{
		"name": "Baby Yoda",
		"identifier": "i3",
		"length": 10
	},
	{
		"name": "Baby Yoda",
		"identifier": "i4",
		"length": 10
	},
	{
		"name": "Baby Yoda",
		"identifier": "i5",
		"length": 10
	},
	{
		"name": "Baby Yoda",
		"identifier": "i6",
		"length": 10
	},
	{
		"name": "Baby Yoda",
		"identifier": "j1",
		"length": 25
	},
	{
		"name": "Baby Yoda",
		"identifier": "j2",
		"length": 20
	},
	{
		"name": "Baby Yoda",
		"identifier": "j3",
		"length": 20
	},
	{
		"name": "Baby Yoda",
		"identifier": "j4",
		"length": 28
	},
	{
		"name": "Baby Yoda",
		"identifier": "j5",
		"length": 26
	},
	{
		"name": "Baby Yoda",
		"identifier": "j6",
		"length": 24
	},
	{
		"name": "Baby Yoda",
		"identifier": "j7",
		"length": 26
	},
	{
		"name": "Baby Yoda",
		"identifier": "j8",
		"length": 21
	},
	{
		"name": "Baby Yoda",
		"identifier": "j9",
		"length": 24
	}
]